azure/mgmt/hanaonazure/__init__.py
azure/mgmt/hanaonazure/_configuration.py
azure/mgmt/hanaonazure/_hana_management_client.py
azure/mgmt/hanaonazure/_version.py
azure/mgmt/hanaonazure/aio/__init__.py
azure/mgmt/hanaonazure/aio/_configuration.py
azure/mgmt/hanaonazure/aio/_hana_management_client.py
azure/mgmt/hanaonazure/aio/operations/__init__.py
azure/mgmt/hanaonazure/aio/operations/_operations.py
azure/mgmt/hanaonazure/aio/operations/_provider_instances_operations.py
azure/mgmt/hanaonazure/aio/operations/_sap_monitors_operations.py
azure/mgmt/hanaonazure/models/__init__.py
azure/mgmt/hanaonazure/models/_hana_management_client_enums.py
azure/mgmt/hanaonazure/models/_models.py
azure/mgmt/hanaonazure/models/_models_py3.py
azure/mgmt/hanaonazure/operations/__init__.py
azure/mgmt/hanaonazure/operations/_operations.py
azure/mgmt/hanaonazure/operations/_provider_instances_operations.py
azure/mgmt/hanaonazure/operations/_sap_monitors_operations.py
azure_mgmt_hanaonazure-1.0.0.dist-info/METADATA
azure_mgmt_hanaonazure-1.0.0.dist-info/WHEEL
azure_mgmt_hanaonazure-1.0.0.dist-info/top_level.txt
azure_mgmt_hanaonazure-1.0.0.dist-info/RECORD
